<?xml version="1.0" encoding="UTF-8" standalone="yes"?>
<gipmds:rapport xmlns:xsi="http://www.w3.org/2001/XMLSchema-instance" xmlns:gipmds="http://www.gip-mds.fr/" type="117" profil="DSN" version="v02r03" xsi:schemaLocation="http://www.gip-mds.fr/ dsn_bilans_v02r03.xsd">
    <envoi>
        <envoi_identification>
            <idflux>F1LP.xkyhhmmq7AhZAiVtkf</idflux>
            <emetteur_siret>12345095000014</emetteur_siret>
            <date_reception>2023-06-14</date_reception>
            <heure_reception>09:17:58</heure_reception>
        </envoi_identification>
        <envoi_bilan>
            <envoi_etat>OK</envoi_etat>
        </envoi_bilan>
    </envoi>
    <declaration>
        <declaration_identification>
            <rang>1</rang>
            <SIREN>999403349</SIREN>
            <nic_affectation>00025</nic_affectation>
        </declaration_identification>
        <declaration_bilan>
            <etat>OK</etat>
        </declaration_bilan>
    </declaration>
    <communication>
        <information_collective type="bmcc">
            <calcul date_calcul="2023-06-08T15:56:37" phase="30">
                <information>
                    <donnees_clefs>
                        <rubriques>
                            <rubrique_date name="dateDebutEffet">2023-09-01</rubrique_date>
                            <rubrique_date name="dateFinEffet">2024-08-31</rubrique_date>
                        </rubriques>
                    </donnees_clefs>
                    <donnees_paie>
                        <taux part="patronale">3.15</taux>
                        <taux part="CCP">3.12</taux>
                    </donnees_paie>
                    <donnees_declaration>
                        <rubriques>
                            <rubrique_string name="identifiantTaux">999403349_30_2023_20230608</rubrique_string>
                            <rubrique_date name="dateCalculTauxContribution">2023-06-08</rubrique_date>
                        </rubriques>
                    </donnees_declaration>
                    <donnees_complement>
                        <rubriques>
                            <rubrique_date name="infoDateDebut">2022-07-01</rubrique_date>
                            <rubrique_date name="infoDateFin">2023-06-30</rubrique_date>
                            <rubrique_integer name="infoNombreSeparations">16</rubrique_integer>
                            <rubrique_string name="identifiantRegularisation">020000000049</rubrique_string>
                            <rubrique_string name="codeMotifRegularisation">05</rubrique_string>
                        </rubriques>
                    </donnees_complement>
                </information>
            </calcul>
        </information_collective>
    </communication>
</gipmds:rapport>
